Metadata-Version: 1.0
Name: new-crazy
Version: 0.2
Summary: The new_crazy in the world
Home-page: https://github.com/ehsangolshani/new_crazy
Author: EhsanGolshani
Author-email: ehsanroman74@gmail.com
License: MIT
Platform: UNKNOWN
